stegoimagex/__init__.py
stegoimagex/batch.py
stegoimagex/compression.py
stegoimagex/core.py
stegoimagex/crypto.py
stegoimagex/decoder.py
stegoimagex/detector.py
stegoimagex/dpe.py
stegoimagex/encoder.py
stegoimagex/integrity.py
stegoimagex/logger.py
stegoimagex-0.0.1.dist-info/METADATA
stegoimagex-0.0.1.dist-info/WHEEL
stegoimagex-0.0.1.dist-info/top_level.txt
stegoimagex-0.0.1.dist-info/RECORD
