Metadata-Version: 2.4
Name: StegoImageX
Version: 0.0.1
Summary: StegoImageX v10.0 — Advanced AES-encrypted, Hash-verified, Dynamic-Position, Compressed Steganography Library.
Home-page: https://github.com/Athallah1234/StegoImageX
Author: ATHALLAH RAJENDRA PUTRA JUNIARTO
Author-email: athallahwork50@gmail.com
Classifier: Programming Language :: Python :: 3
Classifier: Operating System :: OS Independent
Classifier: Topic :: Security :: Cryptography
Classifier: Topic :: Multimedia :: Graphics
Requires-Python: >=3.7
Requires-Dist: Pillow>=9.0.0
Requires-Dist: pycryptodome>=3.10.0
Dynamic: author
Dynamic: author-email
Dynamic: classifier
Dynamic: description
Dynamic: description-content-type
Dynamic: home-page
Dynamic: requires-dist
Dynamic: requires-python
Dynamic: summary
